limetrend/__init__.py
limetrend/aws_client.py
limetrend/cli.py
limetrend/dynamodb.py
limetrend/report.py
limetrend/templates/dynamodb_report.jinja2
limetrend-0.2.0.dist-info/METADATA
limetrend-0.2.0.dist-info/WHEEL
limetrend-0.2.0.dist-info/entry_points.txt
limetrend-0.2.0.dist-info/RECORD
